py_deployer/LICENSE
py_deployer/pydeploy.py
py_deployer/app/__init__.py
py_deployer/app/arguments.py
py_deployer/app/config.py
py_deployer/app/main.py
py_deployer/app/settings.py
py_deployer/app/ssh_client.py
py_deployer/deploy/config_default.yaml
py_deployer-1.7.5.dist-info/LICENSE.txt
py_deployer-1.7.5.dist-info/METADATA
py_deployer-1.7.5.dist-info/WHEEL
py_deployer-1.7.5.dist-info/entry_points.txt
py_deployer-1.7.5.dist-info/top_level.txt
py_deployer-1.7.5.dist-info/RECORD
