Metadata-Version: 2.1
Name: py-deployer
Version: 1.7.5
Summary: Lightweight package to execute zero-downtime deployment on Linux servers
Home-page: https://github.com/best-practice-src/py-deployer
Author: Fabrizio Fubelli
Author-email: fabrizio@fubelli.org
License: UNKNOWN
Project-URL: Source, https://github.com/best-practice-src/py-deployer/blob/main/README.md
Project-URL: Tracker, https://github.com/best-practice-src/py-deployer/issues
Keywords: deployment python releases git zero-downtime ssh
Platform: UNKNOWN
Classifier: Programming Language :: Python :: 3
Classifier: License :: OSI Approved :: GNU General Public License v3 or later (GPLv3+)
Classifier: Operating System :: Unix
Classifier: Development Status :: 4 - Beta
Classifier: Environment :: Console
Classifier: Natural Language :: English
Classifier: Topic :: Software Development :: Build Tools
Classifier: Topic :: Software Development :: Version Control :: Git
Classifier: Topic :: System
Classifier: Topic :: Utilities
Requires-Python: >=3.6
Requires-Dist: argparse
Requires-Dist: gitpython
Requires-Dist: giturlparse
Requires-Dist: paramiko
Requires-Dist: pathlib
Requires-Dist: pyyaml
